{"styles": [{"id": "road_labels_pedestrian", "styleSet": "tilezen_lines", "when": ["all", ["ref", "Is.Roads.Layer"], ["ref", "Is.Street.Pedestrian"], ["!", ["ref", "Is.RailFerry"]]], "technique": "text", "description": "Pedestrian Labels", "category": "pedestrian-labels", "minZoomLevel": ["ref", "Street.Pedestrian.MinZoomLevel"], "attr": {"margin": ["ref", "Default.Margin"], "persisting-margin-reducing": ["ref", "Default.PersistingMargin.Reducing"], "font": ["ref", "Default.Font"], "shape": "line", "vertical-alignment": "Dynamic", "replaceable": true, "new-label-spread-frames": 10, "fade-time": 0.3, "far-threshold": 0.85, "far-threshold-range": 0.015, "polyline-padding-px": 2, "dual-language-leading-space": ["ppi-scale", ["ref", "Label.DualLanguage.Leading"], ["ref", "ScalePPI.Labels"]], "softdepth": ["ref", "SoftDepth.Threshold"], "anchor-point-density": ["step", ["zoom"], 5, 8, 20, 16, 40], "line-width": ["case", ["ref", "Is.Unpaved"], ["world-scale", ["ref", "Street.Pedestrian.Unpaved.Width"]], ["ref", "Internal.Street.Pedestrian.LineWidthZoom"]], "color": ["case", ["ref", "Is.Unpaved"], ["ref", "Street.Pedestrian.Label.Unpaved.Color"], ["ref", "Street.Pedestrian.Label.Color"]], "outline-color": ["case", ["ref", "Is.Unpaved"], ["ref", "Street.Pedestrian.Label.Unpaved.Outline.Color"], ["ref", "Street.Pedestrian.Label.Outline.Color"]], "size": ["ppi-scale", ["ref", "Street.Pedestrian.Label.Size"], ["ref", "ScalePPI.Labels"]], "outline-size": ["ppi-scale", ["ref", "Street.Pedestrian.Label.Outline.Width"], ["ref", "ScalePPI.Labels"]]}}, {"id": "roads_pedestrian", "styleSet": "tilezen_lines", "when": ["all", ["ref", "Is.Roads.Layer"], ["!", ["ref", "Is.Japan.HasPolygonalRoads"]], ["!", ["ref", "Is.RailFerry"]], ["!", ["ref", "Is.Ski.Downhill"]], ["ref", "Is.Street.Pedestrian"]], "technique": "line", "description": "Pedestrian Line", "category": ["ref", "Internal.Street.Pedestrian.RenderPass"], "minZoomLevel": ["ref", "Street.Pedestrian.MinZoomLevel"], "attr": {"cap": "butt", "color": ["ref", "Internal.Street.Pedestrian.Color"], "fillcolor": ["ref", "Transparent.Color"], "width": ["case", ["ref", "Is.Unpaved"], ["world-scale", ["ref", "Street.Pedestrian.Unpaved.Width"]], ["world-scale", ["ref", "Street.Pedestrian.Width"]]], "dasharray": ["case", ["ref", "Is.UnderConstruction"], ["make-vector", ["world-discrete-scale", ["ref", "Street.Pedestrian.Construction.Gap.Length"]], ["world-discrete-scale", ["ref", "Street.Pedestrian.Construction.Dash.Length"]], 0, 0], ["make-vector", ["world-discrete-scale", ["ref", "Street.Pedestrian.Gap.Length"]], ["world-discrete-scale", ["ref", "Street.Pedestrian.Dash.Length"]], 0, 0]], "smooth-steps": ["make-vector", 4, 0.5]}}, {"id": "road_outlines_pedestrian", "styleSet": "tilezen_lines", "when": ["all", ["ref", "Is.Roads.Layer"], ["!", ["ref", "Is.Japan.HasPolygonalRoads"]], ["!", ["ref", "Is.RailFerry"]], ["ref", "Is.Street.Pedestrian"]], "technique": "line", "description": "Pedestrian Outline", "category": ["case", ["ref", "Is.Tunnel"], "tunnel-outline-pedestrian", ["ref", "Is.Bridge"], "bridge-outline-pedestrian", ["ref", "Is.Unpaved"], "unpaved-outline-pedestrian", "pedestrian-outline"], "minZoomLevel": ["ref", "Street.Pedestrian.MinZoomLevel"], "attr": {"cap": "butt", "color": ["case", ["ref", "Is.Unpaved"], ["ref", "Street.Pedestrian.Unpaved.Outline.Color"], ["ref", "Street.Pedestrian.Outline.Color"]], "fillcolor": ["case", ["all", ["ref", "Is.Tunnel"], ["!", ["ref", "Is.UnderConstruction"]]], "#00000000", ["ref", "Transparent.Color"]], "width": ["case", ["ref", "Is.Unpaved"], ["case", ["<=", ["ref", "Street.Pedestrian.Unpaved.Outline.Width"], 0], 0, ["world-scale", ["+", ["*", 2, ["ref", "Street.Pedestrian.Unpaved.Outline.Width"]], ["ref", "Street.Pedestrian.Unpaved.Width"]]]], ["case", ["<=", ["ref", "Street.Pedestrian.Outline.Width"], 0], 0, ["world-scale", ["+", ["*", 2, ["ref", "Street.Pedestrian.Outline.Width"]], ["ref", "Street.Pedestrian.Width"]]]]], "dasharray": ["case", ["all", ["ref", "Is.Tunnel"], ["!", ["ref", "Is.UnderConstruction"]]], ["ref", "Internal.Street.Tunnel.DashArray"], ["ref", "Is.UnderConstruction"], ["make-vector", ["world-discrete-scale", ["ref", "Street.Pedestrian.Construction.Gap.Length"]], ["world-discrete-scale", ["ref", "Street.Pedestrian.Construction.Dash.Length"]], 0, 0], ["make-vector", ["world-discrete-scale", ["ref", "Street.Pedestrian.Gap.Length"]], ["world-discrete-scale", ["ref", "Street.Pedestrian.Dash.Length"]], 0, 0]], "smooth-steps": ["make-vector", 4, 0.5]}}, {"id": "bridge_baseline_pedestrian", "styleSet": "tilezen_lines", "when": ["all", ["ref", "Is.Roads.Layer"], ["ref", "Is.Bridge"], ["!", ["ref", "Is.Japan.HasPolygonalRoads"]], ["!", ["ref", "Is.RailFerry"]], ["ref", "Is.Street.Pedestrian"]], "technique": "line", "description": "Pedestrian Bridge Baseline", "category": "bridge-baseline-pedestrian", "minZoomLevel": ["ref", "Street.Pedestrian.MinZoomLevel"], "attr": {"cap": "butt", "color": ["ref", "Street.Pedestrian.Bridge.Baseline.Color"], "fillcolor": ["ref", "Transparent.Color"], "width": ["case", ["<=", ["ref", "Street.Pedestrian.Width"], 0], 0, ["world-scale", ["ref", "Street.Pedestrian.Bridge.Baseline.Width"]]], "dasharray": ["case", ["ref", "Is.UnderConstruction"], ["make-vector", ["world-discrete-scale", ["ref", "Street.Pedestrian.Construction.Gap.Length"]], ["world-discrete-scale", ["ref", "Street.Pedestrian.Construction.Dash.Length"]], 0, 0], null], "smooth-steps": ["make-vector", 4, 0.75]}}, {"id": "bridge_baseline_outlines_pedestrian", "styleSet": "tilezen_lines", "when": ["all", ["ref", "Is.Roads.Layer"], ["ref", "Is.Bridge"], ["!", ["ref", "Is.Japan.HasPolygonalRoads"]], ["!", ["ref", "Is.RailFerry"]], ["ref", "Is.Street.Pedestrian"]], "technique": "line", "description": "Pedestrian Bridge Extra Outline", "category": "bridge-outline-pedestrian-extra", "minZoomLevel": ["ref", "Street.Pedestrian.MinZoomLevel"], "attr": {"cap": "butt", "color": ["ref", "Street.Pedestrian.Bridge.Color"], "fillcolor": ["ref", "Transparent.Color"], "width": ["case", ["<=", ["ref", "Street.Pedestrian.Width"], 0], 0, ["world-scale", ["+", ["*", 2, ["ref", "Street.Pedestrian.Bridge.Outline.Width"]], ["ref", "Street.Pedestrian.Bridge.Baseline.Width"]]]], "dasharray": ["case", ["ref", "Is.UnderConstruction"], ["make-vector", ["world-discrete-scale", ["ref", "Street.Pedestrian.Construction.Gap.Length"]], ["world-discrete-scale", ["ref", "Street.Pedestrian.Construction.Dash.Length"]], 0, 0], null], "smooth-steps": ["make-vector", 4, 0.75]}}]}